organizations/__init__.py
organizations/abstractions.py
organizations/admin.py
organizations/apps.py
organizations/enums.py
organizations/forms.py
organizations/models.py
organizations/serializers.py
organizations/service.py
organizations/signals.py
organizations/tasks.py
organizations/tests.py
organizations/urls.py
organizations/views.py
organizations/did_factory/__init__.py
organizations/did_factory/abstractions.py
organizations/did_factory/context.py
organizations/did_factory/factory.py
organizations/did_factory/models.py
organizations/did_factory/strategy.py
organizations/migrations/0001_initial.py
organizations/migrations/0002_organization_networks.py
organizations/migrations/0003_alter_organization_networks.py
organizations/migrations/0004_alter_organization_email_and_more.py
organizations/migrations/0005_subject_alter_organization_networks_and_more.py
organizations/migrations/0006_alter_organization_networks_and_more.py
organizations/migrations/0007_alter_issuer_active.py
organizations/migrations/0008_alter_organization_networks.py
organizations/migrations/0009_issuer_name.py
organizations/migrations/0010_alter_organization_name.py
organizations/migrations/0011_issuer_did.py
organizations/migrations/0012_organization_use_did_alter_organization_email_and_more.py
organizations/migrations/0013_alter_organizationkeys_options.py
organizations/migrations/__init__.py
organizations-0.1.4.dist-info/LICENSE
organizations-0.1.4.dist-info/METADATA
organizations-0.1.4.dist-info/WHEEL
organizations-0.1.4.dist-info/top_level.txt
organizations-0.1.4.dist-info/RECORD
